exceptbot/__init__.py
exceptbot/admin.py
exceptbot/apps.py
exceptbot/forms.py
exceptbot/middleware.py
exceptbot/models.py
exceptbot/tests.py
exceptbot/urls.py
exceptbot/views.py
exceptbot/static/exceptbot/github-banner.jpg
exceptbot/static/exceptbot/icon.gif
exceptbot/static/exceptbot/icon.png
exceptbot/static/exceptbot/no-issues.jpg
exceptbot/templates/exceptbot/ai_suggestion.html
exceptbot/templates/exceptbot/base.html
exceptbot/templates/exceptbot/detail.html
exceptbot/templates/exceptbot/error_message.html
exceptbot/templates/exceptbot/file_content.html
exceptbot/templates/exceptbot/list.html
exceptbot/templates/exceptbot/settings.html
test_project/__init__.py
test_project/asgi.py
test_project/middleware.py
test_project/settings.py
test_project/urls.py
test_project/wsgi.py
exceptbot-1.0.11.dist-info/LICENSE.md
exceptbot-1.0.11.dist-info/METADATA
exceptbot-1.0.11.dist-info/WHEEL
exceptbot-1.0.11.dist-info/top_level.txt
exceptbot-1.0.11.dist-info/RECORD
