Metadata-Version: 2.1
Name: exceptbot
Version: 1.0.11
Summary: Exception Logger with AI Suggestions for Django
Home-page: https://exceptbot.com
Author: Brian Risk
Author-email: geneffects@gmail.com
License: # License
Classifier: Programming Language :: Python :: 3
Classifier: Operating System :: OS Independent
Classifier: License :: Other/Proprietary License
Requires-Python: >=3.6
License-File: LICENSE.md
Requires-Dist: openai >=1.3.7
Requires-Dist: Django
